chem/__init__.py
chem/chemcalc.py
chem/chemtools.py
chem/miller.py
chem-2.0.0.dist-info/licenses/LICENSE
chem-2.0.0.dist-info/METADATA
chem-2.0.0.dist-info/WHEEL
chem-2.0.0.dist-info/top_level.txt
chem-2.0.0.dist-info/RECORD
